README.txt
setup.py
zbxsend.py
zbxsend.egg-info/PKG-INFO
zbxsend.egg-info/SOURCES.txt
zbxsend.egg-info/dependency_links.txt
zbxsend.egg-info/top_level.txt