Metadata-Version: 1.1
Name: zbxsend
Version: 0.1.5
Summary: Module used to send metrics to Zabbix.
Home-page: https://github.com/pistolero/zbxsend
Author: Sergey Kirillov
Author-email: sergey.kirillov@gmail.com
License: BSD
Platform: UNKNOWN
Classifier: License :: OSI Approved :: BSD License
